falcon_pagination/__init__.py
falcon_pagination/offset_pagination_hook.py
falcon_pagination-0.0.1.dist-info/DESCRIPTION.rst
falcon_pagination-0.0.1.dist-info/METADATA
falcon_pagination-0.0.1.dist-info/RECORD
falcon_pagination-0.0.1.dist-info/WHEEL
falcon_pagination-0.0.1.dist-info/metadata.json
falcon_pagination-0.0.1.dist-info/top_level.txt
