Metadata-Version: 2.0
Name: falcon-pagination
Version: 0.0.1
Summary: Falcon pagination helper
Home-page: https://github.com/darkheir/falcon-pagination-hook
Author: Raphael Cohen
Author-email: raphael.cohen.utt@gmail.com
License: MIT
Keywords: falcon pagination api
Platform: UNKNOWN
Classifier: Development Status :: 5 - Production/Stable
Classifier: Intended Audience :: Developers
Classifier: Operating System :: OS Independent
Classifier: Programming Language :: Python
Classifier: Programming Language :: Python :: 3
Classifier: Programming Language :: Python :: 3.6
Classifier: Topic :: Software Development :: Libraries
Requires-Dist: falcon (>=0.3)
